jupyterlab_zethus/__init__.py
jupyterlab_zethus/_version.py
jupyterlab_zethus/handlers.py
jupyterlab_zethus/labextension/package.json
jupyterlab_zethus/labextension/schemas/jupyterlab-zethus/package.json.orig
jupyterlab_zethus/labextension/schemas/jupyterlab-zethus/plugin.json
jupyterlab_zethus/labextension/static/118.7f75395267dbe9083e87.js
jupyterlab_zethus/labextension/static/534.5bd19bee0fb5a0575216.js
jupyterlab_zethus/labextension/static/remoteEntry.ecd3de7b00d99e6237ab.js
jupyterlab_zethus/labextension/static/style.js
jupyterlab_zethus/zethus/1.index.5cba51a5817e6b4ede67.js
jupyterlab_zethus/zethus/1.index.5cba51a5817e6b4ede67.js.map
jupyterlab_zethus/zethus/2b9b4872cd25494093c1eb14f0264a0b.svg
jupyterlab_zethus/zethus/5bbcdfca599323ba0603.module.wasm
jupyterlab_zethus/zethus/EditorControls.js
jupyterlab_zethus/zethus/favicon.ico
jupyterlab_zethus/zethus/index.5cba51a5817e6b4ede67.js
jupyterlab_zethus/zethus/index.5cba51a5817e6b4ede67.js.map
jupyterlab_zethus/zethus/index.html
jupyterlab_zethus/zethus/logo.svg
jupyterlab_zethus/zethus/screenshot.png
jupyterlab_zethus/zethus/zethus.svg
jupyterlab_zethus/zethus/zethus_full.svg
jupyterlab_zethus/zethus/zethus_mark.svg
jupyterlab_zethus/zethus/forklift/forklift.stl
jupyterlab_zethus/zethus/image/viz/viz-image.png
jupyterlab_zethus/zethus/image/viz/viz-interactive-marker.png
jupyterlab_zethus/zethus/image/viz/viz-laserscan.png
jupyterlab_zethus/zethus/image/viz/viz-map.png
jupyterlab_zethus/zethus/image/viz/viz-marker.png
jupyterlab_zethus/zethus/image/viz/viz-markerarray.png
jupyterlab_zethus/zethus/image/viz/viz-odometry.png
jupyterlab_zethus/zethus/image/viz/viz-path.png
jupyterlab_zethus/zethus/image/viz/viz-point.png
jupyterlab_zethus/zethus/image/viz/viz-pointcloud.png
jupyterlab_zethus/zethus/image/viz/viz-pose.png
jupyterlab_zethus/zethus/image/viz/viz-posearray.png
jupyterlab_zethus/zethus/image/viz/viz-range.png
jupyterlab_zethus/zethus/image/viz/viz-robotmodel.png
jupyterlab_zethus-1.3.1.dist-info/LICENSE.txt
jupyterlab_zethus-1.3.1.dist-info/METADATA
jupyterlab_zethus-1.3.1.dist-info/WHEEL
jupyterlab_zethus-1.3.1.dist-info/top_level.txt
jupyterlab_zethus-1.3.1.dist-info/RECORD
