Metadata-Version: 2.1
Name: jupyterlab-zethus
Version: 1.3.1
Summary: A JupyterLab extension.
Home-page: https://github.com/robostack/jupyterlab-zethus
Author: Wolf Vollprecht
Author-email: w.vollprecht@gmail.com
License: BSD-3-Clause
Keywords: Jupyter,JupyterLab,JupyterLab3
Platform: Linux
Platform: Mac OS X
Platform: Windows
Classifier: License :: OSI Approved :: BSD License
Classifier: Programming Language :: Python
Classifier: Programming Language :: Python :: 3
Classifier: Programming Language :: Python :: 3.6
Classifier: Programming Language :: Python :: 3.7
Classifier: Programming Language :: Python :: 3.8
Classifier: Programming Language :: Python :: 3.9
Classifier: Framework :: Jupyter
Requires-Python: >=3.6
License-File: LICENSE.txt
Requires-Dist: jupyter-server (<2,>=1.6)
